sdssdb/__init__.py
sdssdb/connection.py
sdssdb/exceptions.py
sdssdb/etc/sdssdb.yml
sdssdb/peewee/__init__.py
sdssdb/peewee/lvmdb/__init__.py
sdssdb/peewee/lvmdb/gortdb.py
sdssdb/peewee/lvmdb/lvmopsdb.py
sdssdb/peewee/operationsdb/__init__.py
sdssdb/peewee/operationsdb/apogeeqldb.py
sdssdb/peewee/operationsdb/mangadb.py
sdssdb/peewee/operationsdb/platedb.py
sdssdb/peewee/sdss5db/__init__.py
sdssdb/peewee/sdss5db/apogee_drpdb.py
sdssdb/peewee/sdss5db/astradb.py
sdssdb/peewee/sdss5db/boss_drp.py
sdssdb/peewee/sdss5db/catalogdb.py
sdssdb/peewee/sdss5db/deprecated.py
sdssdb/peewee/sdss5db/lvmopsdb.py
sdssdb/peewee/sdss5db/opsdb.py
sdssdb/peewee/sdss5db/sandbox.py
sdssdb/peewee/sdss5db/targetdb.py
sdssdb/peewee/sdss5db/vizdb.py
sdssdb/sqlalchemy/__init__.py
sdssdb/sqlalchemy/archive/__init__.py
sdssdb/sqlalchemy/archive/sas.py
sdssdb/sqlalchemy/mangadb/__init__.py
sdssdb/sqlalchemy/mangadb/auxdb.py
sdssdb/sqlalchemy/mangadb/dapdb.py
sdssdb/sqlalchemy/mangadb/datadb.py
sdssdb/sqlalchemy/mangadb/sampledb.py
sdssdb/sqlalchemy/operationsdb/__init__.py
sdssdb/sqlalchemy/operationsdb/apogeeqldb.py
sdssdb/sqlalchemy/operationsdb/mangadb.py
sdssdb/sqlalchemy/operationsdb/platedb.py
sdssdb/sqlalchemy/operationsdb/tools/__init__.py
sdssdb/sqlalchemy/operationsdb/tools/astrodatetime.py
sdssdb/sqlalchemy/operationsdb/tools/convert.py
sdssdb/sqlalchemy/operationsdb/tools/dateObs2HA.py
sdssdb/sqlalchemy/operationsdb/tools/geometry.py
sdssdb/sqlalchemy/operationsdb/tools/moon.py
sdssdb/sqlalchemy/operationsdb/tools/sun.py
sdssdb/sqlalchemy/sdss5db/__init__.py
sdssdb/sqlalchemy/sdss5db/apogee_drpdb.py
sdssdb/sqlalchemy/sdss5db/astradb.py
sdssdb/sqlalchemy/sdss5db/boss_drp.py
sdssdb/sqlalchemy/sdss5db/catalogdb.py
sdssdb/sqlalchemy/sdss5db/opsdb.py
sdssdb/sqlalchemy/sdss5db/targetdb.py
sdssdb/sqlalchemy/sdss5db/vizdb.py
sdssdb/utils/__init__.py
sdssdb/utils/adaptors.py
sdssdb/utils/ingest.py
sdssdb/utils/internals.py
sdssdb/utils/registry.py
sdssdb/utils/schemadisplay.py
sdssdb-0.13.5.dist-info/licenses/LICENSE.md
sdssdb-0.13.5.dist-info/METADATA
sdssdb-0.13.5.dist-info/WHEEL
sdssdb-0.13.5.dist-info/top_level.txt
sdssdb-0.13.5.dist-info/RECORD
